optlearn/__init__.py
optlearn/opt.py
optlearn/version.py
optuna_learn-0.1.0.dist-info/LICENSE
optuna_learn-0.1.0.dist-info/METADATA
optuna_learn-0.1.0.dist-info/WHEEL
optuna_learn-0.1.0.dist-info/top_level.txt
optuna_learn-0.1.0.dist-info/RECORD
